pymorphy_spacy_disambiguation-0.1.5.dist-info/METADATA
pymorphy_spacy_disambiguation-0.1.5.dist-info/WHEEL
pymorphy_spacy_disambiguation-0.1.5.dist-info/entry_points.txt
pymorphy_spacy_disambiguation-0.1.5.dist-info/licenses/LICENSE
pymorphy_spacy_disambiguation/__init__.py
pymorphy_spacy_disambiguation/disamb.py
pymorphy_spacy_disambiguation-0.1.5.dist-info/RECORD
