Metadata-Version: 2.1
Name: pymorphy-spacy-disambiguation
Version: 0.1.5
Summary: Use spacy to disambiguate pymorphy3 morphology analyses.
Author-Email: "Hamotskyi, Serhii" <serhii@serhii.net>
Requires-Python: <4.0,>=3.7
Requires-Dist: pip>=24.0
Requires-Dist: pymorphy3>=2.0.2
Requires-Dist: pymorphy3-dicts-uk>=2.4.1.1.1663094765
Requires-Dist: russian-tagsets>=0.6
Requires-Dist: spacy>=3.7.5
